aidu/__init__.py
aidu/__version__.py
aidu/aidu.py
aidu-0.0.1.dist-info/LICENSE
aidu-0.0.1.dist-info/METADATA
aidu-0.0.1.dist-info/WHEEL
aidu-0.0.1.dist-info/top_level.txt
aidu-0.0.1.dist-info/RECORD
