Metadata-Version: 2.1
Name: aidu
Version: 0.0.1
Summary: Artifical Intelligence, Do
Home-page: https://git.udia.ca/udia-software/aidu
Author: Alexander W. Wong
Author-email: alex@udia.ca
License: MIT
Platform: UNKNOWN
Classifier: License :: OSI Approved :: Apache Software License
Classifier: Programming Language :: Python
Classifier: Programming Language :: Python :: 3
Classifier: Programming Language :: Python :: 3.6
Requires-Python: >=3.6.0
